pinterest/__init__.py
pinterest/api.py
pinterest/asynchronous/__init__.py
pinterest/asynchronous/ad_accounts.py
pinterest/asynchronous/boards.py
pinterest/asynchronous/catalogs.py
pinterest/asynchronous/media.py
pinterest/asynchronous/pins.py
pinterest/asynchronous/user_account.py
pinterest/base_endpoint.py
pinterest/exceptions.py
pinterest/models/__init__.py
pinterest/models/ad_account.py
pinterest/models/analytics.py
pinterest/models/base.py
pinterest/models/board.py
pinterest/models/catalog.py
pinterest/models/common.py
pinterest/models/media.py
pinterest/models/pin.py
pinterest/models/user_account.py
pinterest/sync/__init__.py
pinterest/sync/ad_accounts.py
pinterest/sync/boards.py
pinterest/sync/catalogs.py
pinterest/sync/media.py
pinterest/sync/pins.py
pinterest/sync/user_account.py
pinterest/utils/__init__.py
pinterest/utils/params.py
python_pinterest-0.2.0.dist-info/WHEEL
python_pinterest-0.2.0.dist-info/METADATA
python_pinterest-0.2.0.dist-info/RECORD
