Metadata-Version: 2.1
Name: python-pinterest
Version: 0.2.0
Summary: A simple Python wrapper for Pinterest REST API (Beta) (5.x) ✨ 🍰 ✨
Home-page: https://github.com/sns-sdks/python-pinterest
License: MIT
Keywords: pinterest,pinterest sdk,pinterest api v5
Author: ikaroskun
Author-email: merle.liukun@gmail.com
Requires-Python: >=3.6.2,<4.0.0
Classifier: License :: OSI Approved :: MIT License
Classifier: Programming Language :: Python :: 3
Classifier: Programming Language :: Python :: 3 :: Only
Classifier: Programming Language :: Python :: 3.10
Classifier: Programming Language :: Python :: 3.6
Classifier: Programming Language :: Python :: 3.7
Classifier: Programming Language :: Python :: 3.8
Classifier: Programming Language :: Python :: 3.9
Classifier: Programming Language :: Python :: Implementation :: CPython
Classifier: Topic :: Software Development :: Libraries :: Python Modules
Requires-Dist: Authlib (>=0.15.5,<0.16.0)
Requires-Dist: dataclasses-json (>=0.5.6,<0.6.0)
Requires-Dist: httpx (==0.22.0)
Project-URL: Repository, https://github.com/sns-sdks/python-pinterest
